pgljupyter/__init__.py
pgljupyter/_frontend.py
pgljupyter/_version.py
pgljupyter/editors.py
pgljupyter/magics.py
pgljupyter/widgets.py
pgljupyter/labextension/package.json
pgljupyter/labextension/static/121.6842de1819d06f8cb102.js
pgljupyter/labextension/static/121.6842de1819d06f8cb102.js.LICENSE.txt
pgljupyter/labextension/static/138.45829ecf88554cffa0ac.js
pgljupyter/labextension/static/14.031b939c36b83060c546.js
pgljupyter/labextension/static/14.031b939c36b83060c546.js.LICENSE.txt
pgljupyter/labextension/static/212.c8680d504eac6a41e105.js
pgljupyter/labextension/static/212.c8680d504eac6a41e105.js.LICENSE.txt
pgljupyter/labextension/static/230.b7d0a775aa0e5fc1f54f.js
pgljupyter/labextension/static/386.075d4a3e698acf160a06.js
pgljupyter/labextension/static/386.075d4a3e698acf160a06.js.LICENSE.txt
pgljupyter/labextension/static/44.8cac7527e4c4a75cfdbc.js
pgljupyter/labextension/static/44.8cac7527e4c4a75cfdbc.js.LICENSE.txt
pgljupyter/labextension/static/568.9369f186a624bfefe6da.js
pgljupyter/labextension/static/581.05876328b5074d8cdd38.js
pgljupyter/labextension/static/61.0ef581283e5c913c863b.js
pgljupyter/labextension/static/61.0ef581283e5c913c863b.js.LICENSE.txt
pgljupyter/labextension/static/74.2d0228ba5d61f4416a60.js
pgljupyter/labextension/static/74.2d0228ba5d61f4416a60.js.LICENSE.txt
pgljupyter/labextension/static/758.8adf4e334c7111186799.js
pgljupyter/labextension/static/758.8adf4e334c7111186799.js.LICENSE.txt
pgljupyter/labextension/static/810.54815891312b58e00119.js
pgljupyter/labextension/static/810.54815891312b58e00119.js.LICENSE.txt
pgljupyter/labextension/static/816.76acf194fb093ce9e297.js
pgljupyter/labextension/static/816.76acf194fb093ce9e297.js.LICENSE.txt
pgljupyter/labextension/static/880.6ce493f16b575b4c083b.js
pgljupyter/labextension/static/880.6ce493f16b575b4c083b.js.LICENSE.txt
pgljupyter/labextension/static/924.1bd853b57cc7391b7716.js
pgljupyter/labextension/static/924.1bd853b57cc7391b7716.js.LICENSE.txt
pgljupyter-2.0.0.dist-info/METADATA
pgljupyter-2.0.0.dist-info/WHEEL
pgljupyter-2.0.0.dist-info/top_level.txt
pgljupyter-2.0.0.dist-info/RECORD
