Metadata-Version: 2.1
Name: pgljupyter
Version: 2.0.0
Summary: PlantGL and L-Py Jupyter widgets
Home-page: https://github.com/fredboudon/plantgl-jupyter
License: CeCILL
Keywords: Jupyter,JupyterLab,JupyterLab3
Platform: Linux
Platform: Mac OS X
Platform: Windows
Classifier: License :: OSI Approved :: BSD License
Classifier: Programming Language :: Python
Classifier: Programming Language :: Python :: 3
Classifier: Programming Language :: Python :: 3.7
Classifier: Programming Language :: Python :: 3.8
Classifier: Programming Language :: Python :: 3.9
Classifier: Programming Language :: Python :: 3.10
Classifier: Framework :: Jupyter
Classifier: Framework :: Jupyter :: JupyterLab
Classifier: Framework :: Jupyter :: JupyterLab :: 3
Classifier: Framework :: Jupyter :: JupyterLab :: Extensions
Classifier: Framework :: Jupyter :: JupyterLab :: Extensions :: Prebuilt
Requires-Python: >=3.7
Requires-Dist: openalea.lpy (<4.0.0,>=3.9.0)
Requires-Dist: openalea.plantgl (<4.0.0,>=3.14.0)
